{
  "username": "shawn",
  "email": "none3@none.com",
  "phoneNumber": "0(123)456-7890",
  "password": "",
  "habitTracker": {
    "habits": [
    {
    "habitName" : "Go To Gym",
    "build" : true,
    "quit" : false,
    "daily" : false,
    "weekly" : true,
    "monthly" : false,
    "yearly" : false,
    "timesPerGoalPeriod": 4,
    "countDone": 1,
    "backgroundColor" : "#077187",
    "daysCompleted" : [
      "2022-05-18", 
      "2022-05-19"
      ] 
     },
     {
      "habitName" : "Read 5 Chapters of the Book of Mormon",
      "build" : true,
      "quit" : false,
      "daily" : false,
      "weekly" : true,
      "monthly" : false,
      "yearly" : false,
      "timesPerGoalPeriod": 5,
      "countDone": 1,
      "backgroundColor" : "#077187",
      "daysCompleted" : [
        "2022-05-18", 
        "2022-05-19"
        ] 
       }
    ]
  },
    "chosenMoods" : {
      "moods" : [
      {
      "day": "2022-05-18",
      "moodName": "Happy"
        },
        {
        "day": "2022-05-19",
        "moodName": "Happy"
        }
       ]
     }
  }
